adams/__init__.py
adams/db_maker.py
adams/matcher.py
adams/tool_kit.py
adams/scripts/compare_all.py
adams-1.0.1.data/scripts/compare_all.py
adams-1.0.1.dist-info/LICENSE
adams-1.0.1.dist-info/METADATA
adams-1.0.1.dist-info/WHEEL
adams-1.0.1.dist-info/top_level.txt
adams-1.0.1.dist-info/RECORD
