Metadata-Version: 2.1
Name: adams
Version: 1.0.1
Summary: this is a program for fast protein structure search
Home-page: https://github.com/young55775/ADAMS-developing
Author: Guo_Zhengyang
Author-email: guozy23@mails.tsinghua.edu.cn
License: GNU-GPL 3.0
Classifier: Programming Language :: Python :: 3
Classifier: Development Status :: 4 - Beta
License-File: LICENSE
Requires-Dist: numpy
Requires-Dist: opencv-python
Requires-Dist: scipy
Requires-Dist: tqdm
Requires-Dist: biopython
Requires-Dist: GPUtil
